bitranox_template_py_lib/__init__.py
bitranox_template_py_lib/__init__conf__.py
bitranox_template_py_lib/__main__.py
bitranox_template_py_lib/behaviors.py
bitranox_template_py_lib/cli.py
bitranox_template_py_lib/py.typed
bitranox_template_py_lib-1.0.3.dist-info/METADATA
bitranox_template_py_lib-1.0.3.dist-info/WHEEL
bitranox_template_py_lib-1.0.3.dist-info/entry_points.txt
bitranox_template_py_lib-1.0.3.dist-info/licenses/LICENSE
bitranox_template_py_lib-1.0.3.dist-info/RECORD
