Metadata-Version: 2.4
Name: bitranox_template_py_lib
Version: 1.0.3
Summary: Template for backward compatible python libs with registered cli commands
Project-URL: Homepage, https://github.com/bitranox/bitranox_template_py_lib
Project-URL: Repository, https://github.com/bitranox/bitranox_template_py_lib.git
Project-URL: Issues, https://github.com/bitranox/bitranox_template_py_lib/issues
Author-email: bitranox <bitranox@gmail.com>
License: MIT
License-File: LICENSE
Keywords: ansi,cli,logging,rich,terminal
Classifier: Environment :: Console
Classifier: License :: OSI Approved :: MIT License
Classifier: Operating System :: OS Independent
Classifier: Programming Language :: Python :: 3
Classifier: Programming Language :: Python :: 3 :: Only
Classifier: Programming Language :: Python :: 3.9
Classifier: Programming Language :: Python :: 3.10
Classifier: Programming Language :: Python :: 3.11
Classifier: Programming Language :: Python :: 3.12
Classifier: Programming Language :: Python :: 3.13
Classifier: Typing :: Typed
Requires-Python: >=3.9
Requires-Dist: rich-click>=1.9.4
Requires-Dist: rtoml>=0.13.0
Provides-Extra: dev
Requires-Dist: bandit<1.9,>=1.8.6; (python_version < '3.10') and extra == 'dev'
Requires-Dist: bandit>=1.9.2; (python_version >= '3.10') and extra == 'dev'
Requires-Dist: build>=1.3.0; extra == 'dev'
Requires-Dist: codecov-cli>=11.2.6; extra == 'dev'
Requires-Dist: import-linter<2.6,>=2.5.2; (python_version < '3.10') and extra == 'dev'
Requires-Dist: import-linter>=2.9; (python_version >= '3.10') and extra == 'dev'
Requires-Dist: pip-audit>=2.10.0; extra == 'dev'
Requires-Dist: pyright>=1.1.407; extra == 'dev'
Requires-Dist: pytest-cov>=7.0.0; extra == 'dev'
Requires-Dist: pytest<9,>=8.4.2; (python_version < '3.10') and extra == 'dev'
Requires-Dist: pytest>=9.0.2; (python_version >= '3.10') and extra == 'dev'
Requires-Dist: rtoml>=0.13.0; extra == 'dev'
Requires-Dist: ruff>=0.14.9; extra == 'dev'
Requires-Dist: setuptools>=80.9.0; extra == 'dev'
Requires-Dist: textual>=6.9.0; extra == 'dev'
Requires-Dist: twine>=6.2.0; extra == 'dev'
